oneq-1.0.0.dist-info/licenses/LICENSE
oneq_cli/__init__.py
oneq_cli/cli.py
oneq_cli/config.py
oneq_cli/exceptions.py
oneq_cli/gemini.py
oneq_cli/tui.py
oneq-1.0.0.dist-info/METADATA
oneq-1.0.0.dist-info/WHEEL
oneq-1.0.0.dist-info/entry_points.txt
oneq-1.0.0.dist-info/top_level.txt
oneq-1.0.0.dist-info/RECORD
