Metadata-Version: 2.4
Name: oneq
Version: 1.0.0
Summary: 1Q: 1 query away from the right one-line command.
Author-email: John Le <john@oj.hn>
License: MIT License
Project-URL: Homepage, https://github.com/9-5/1q
Keywords: cli,ai,commandgen,codegen,devtool
Classifier: Programming Language :: Python :: 3
Classifier: Programming Language :: Python :: 3.8
Classifier: Programming Language :: Python :: 3.9
Classifier: Programming Language :: Python :: 3.10
Classifier: Programming Language :: Python :: 3.11
Classifier: Programming Language :: Python :: 3.12
Classifier: License :: OSI Approved :: MIT License
Classifier: Operating System :: OS Independent
Classifier: Environment :: Console
Classifier: Intended Audience :: Developers
Classifier: Topic :: Software Development :: Code Generators
Classifier: Topic :: Utilities
Classifier: Typing :: Typed
Requires-Python: >=3.8
License-File: LICENSE
Requires-Dist: google-generativeai
Requires-Dist: textual>=0.50.0
Requires-Dist: platformdirs>=3.0.0
Requires-Dist: rich
Requires-Dist: pyperclip>=1.8.0
Provides-Extra: dev
Requires-Dist: pytest; extra == "dev"
Requires-Dist: pytest-cov; extra == "dev"
Requires-Dist: ruff; extra == "dev"
Dynamic: license-file
